tests/test_voipms_client.py
voipms_api/__init__.py
voipms_api/accounts.py
voipms_api/call_hunting.py
voipms_api/dids.py
voipms_api/forwarding.py
voipms_api/general.py
voipms_api/ivr.py
voipms_api/lnp.py
voipms_api/ring_groups.py
voipms_api/sms.py
voipms_api/voicemail.py
voipms_api/voipms_client.py
voipms_api-1.1.5b11.dist-info/LICENSE
voipms_api-1.1.5b11.dist-info/METADATA
voipms_api-1.1.5b11.dist-info/WHEEL
voipms_api-1.1.5b11.dist-info/top_level.txt
voipms_api-1.1.5b11.dist-info/RECORD
