Metadata-Version: 2.1
Name: voipms-api
Version: 1.1.5b11
Summary: A python package to simplify the use of the VoIP.ms API
Author-email: Jose Pineda <hello@joseanmont.com>
Project-URL: Homepage, https://github.com/joseanmont/voipms-api
Project-URL: Issues, https://github.com/joseanmont/voipms-api/issues
Classifier: Programming Language :: Python :: 3
Classifier: License :: OSI Approved :: MIT License
Classifier: Operating System :: OS Independent
Requires-Python: >=3.10
License-File: LICENSE
Requires-Dist: requests>=2.32.3
